pcdscalc/__init__.py
pcdscalc/_version.py
pcdscalc/be_lens_calcs.py
pcdscalc/common.py
pcdscalc/constants.py
pcdscalc/diffraction.py
pcdscalc/pmps.py
pcdscalc/version.py
pcdscalc/xray.py
pcdscalc/tests/__init__.py
pcdscalc/tests/conftest.py
pcdscalc/tests/test_be_lens_calcs.py
pcdscalc/tests/test_common.py
pcdscalc/tests/test_diffraction.py
pcdscalc/tests/test_pmps.py
pcdscalc/tests/test_lens_sets/lens_set
pcdscalc-0.6.1.dist-info/AUTHORS.rst
pcdscalc-0.6.1.dist-info/LICENSE
pcdscalc-0.6.1.dist-info/METADATA
pcdscalc-0.6.1.dist-info/WHEEL
pcdscalc-0.6.1.dist-info/top_level.txt
pcdscalc-0.6.1.dist-info/RECORD
