Metadata-Version: 2.2
Name: pcdscalc
Version: 0.6.1
Summary: PCDS Calculation Routines
Author: SLAC National Accelerator Laboratory
License: Copyright (c) 2023, The Board of Trustees of the Leland Stanford Junior
Classifier: Development Status :: 2 - Pre-Alpha
Classifier: Natural Language :: English
Classifier: Programming Language :: Python :: 3
Requires-Python: >=3.9
License-File: LICENSE
License-File: AUTHORS.rst
Requires-Dist: numpy
Requires-Dist: ophyd
Requires-Dist: periodictable
Requires-Dist: scipy
Requires-Dist: xraydb
Requires-Dist: xraylib
Provides-Extra: test
Requires-Dist: pytest; extra == "test"
Provides-Extra: doc
Requires-Dist: docs-versions-menu; extra == "doc"
Requires-Dist: numpydoc; extra == "doc"
Requires-Dist: recommonmark; extra == "doc"
Requires-Dist: sphinx<7; extra == "doc"
Requires-Dist: sphinx-copybutton; extra == "doc"
Requires-Dist: sphinx_rtd_theme; extra == "doc"
Requires-Dist: sphinxcontrib-jquery; extra == "doc"
